fastertransformer/__init__.py
fastertransformer/libtf_bert.so
fastertransformer-5.0.0.116.dist-info/METADATA
fastertransformer-5.0.0.116.dist-info/WHEEL
fastertransformer-5.0.0.116.dist-info/top_level.txt
fastertransformer-5.0.0.116.dist-info/RECORD
